devart/zohocrm/__init__.py
devart/zohocrm/zohocrm.cp39-win_amd64.pyd
devart/zohocrm/zohocrm.pyi
devart/zohocrm/ZohoCRM/Devart.Python.ZohoEngine.dll
devart/zohocrm/ZohoCRM/sqlite3.dll
devart/zohocrm/sqlalchemy/__init__.py
devart_zohocrm_connector-1.2.0.dist-info/LICENSE
devart_zohocrm_connector-1.2.0.dist-info/METADATA
devart_zohocrm_connector-1.2.0.dist-info/WHEEL
devart_zohocrm_connector-1.2.0.dist-info/top_level.txt
devart_zohocrm_connector-1.2.0.dist-info/RECORD
